test/test_active_set.py
test/test_estimator.py
test/__init__.py
test/test_logistic_regression.py
cyanure-1.1.0.dist-info/RECORD
cyanure-1.1.0.dist-info/LICENSE
cyanure-1.1.0.dist-info/WHEEL
cyanure-1.1.0.dist-info/top_level.txt
cyanure-1.1.0.dist-info/METADATA
cyanure_lib/cyanure_wrap.cpython-37m-darwin.so
cyanure_lib/__init__.py
cyanure/__init__.py
cyanure/logger.py
cyanure/data_processing.py
cyanure/estimators.py
cyanure/.dylibs/libomp.dylib
cyanure/.dylibs/libgfortran.5.dylib
cyanure/.dylibs/libopenblasp-r0.3.21.dylib
cyanure/.dylibs/libquadmath.0.dylib
cyanure/.dylibs/libgcc_s.1.1.dylib
