Metadata-Version: 2.1
Name: cyanure
Version: 1.1.0
Summary: optimization toolbox for machine learning
Home-page: https://inria-thoth.github.io/cyanure/welcome.html
Author: Julien Mairal
Author-email: julien.mairal@inria.fr
License: bsd-3-clause
Platform: UNKNOWN
License-File: LICENSE
Requires-Dist: scikit-learn
Requires-Dist: scipy (<=1.8.1) ; python_version < "3.11"
Requires-Dist: numpy (<=1.23.5) ; python_version < "3.11"
Requires-Dist: scipy (>=1.8.1) ; python_version >= "3.11"
Requires-Dist: numpy (>=1.23.5) ; python_version >= "3.11"
